pyopenxr-1.1.5301.dist-info/licenses/LICENSE
xr/__init__.py
xr/array_field.py
xr/constants.py
xr/custom_functions.py
xr/enums.py
xr/exception.py
xr/functions.py
xr/handle.py
xr/raw_functions.py
xr/resources.py
xr/typedefs.py
xr/version.py
xr/api_layer/__init__.py
xr/api_layer/dynamic_api_layer_base.py
xr/api_layer/layer_path.py
xr/api_layer/loader_interfaces.py
xr/api_layer/raw_functions.py
xr/api_layer/steamvr_linux_destroyinstance_layer.py
xr/api_layer/android/XrApiLayer_api_dump.json
xr/api_layer/android/XrApiLayer_best_practices_validation.json
xr/api_layer/android/XrApiLayer_core_validation.json
xr/api_layer/android/libXrApiLayer_api_dump.so
xr/api_layer/android/libXrApiLayer_best_practices_validation.so
xr/api_layer/android/libXrApiLayer_core_validation.so
xr/api_layer/android/libXrApiLayer_python.so
xr/api_layer/linux/XrApiLayer_api_dump.json
xr/api_layer/linux/XrApiLayer_best_practices_validation.json
xr/api_layer/linux/XrApiLayer_core_validation.json
xr/api_layer/linux/__init__.py
xr/api_layer/linux/libXrApiLayer_api_dump.so
xr/api_layer/linux/libXrApiLayer_best_practices_validation.so
xr/api_layer/linux/libXrApiLayer_core_validation.so
xr/api_layer/linux/libXrApiLayer_python.so
xr/api_layer/windows/XrApiLayer_api_dump.dll
xr/api_layer/windows/XrApiLayer_api_dump.json
xr/api_layer/windows/XrApiLayer_best_practices_validation.dll
xr/api_layer/windows/XrApiLayer_best_practices_validation.json
xr/api_layer/windows/XrApiLayer_core_validation.dll
xr/api_layer/windows/XrApiLayer_core_validation.json
xr/api_layer/windows/XrApiLayer_python.dll
xr/api_layer/windows/__init__.py
xr/ext/__init__.py
xr/ext/EXT/__init__.py
xr/ext/EXT/debug_utils.py
xr/ext/HTCX/__init__.py
xr/ext/HTCX/vive_tracker_interaction.py
xr/ext/KHR/__init__.py
xr/ext/KHR/opengl_enable.py
xr/ext/KHR/opengl_es_enable.py
xr/ext/MND/__init__.py
xr/ext/MND/headless.py
xr/ext/MNDX/egl_enable.py
xr/library/__init__.py
xr/library/libopenxr_loader.so
xr/library/openxr_loader.dll
xr/library/android/libopenxr_loader.so
xr/platform/__init__.py
pyopenxr-1.1.5301.dist-info/METADATA
pyopenxr-1.1.5301.dist-info/WHEEL
pyopenxr-1.1.5301.dist-info/top_level.txt
pyopenxr-1.1.5301.dist-info/RECORD
