Metadata-Version: 2.4
Name: pyopenxr
Version: 1.1.5301
Summary: Unofficial Python bindings for OpenXR VR/AR device access
Author-email: "Christopher M. Bruns" <cmbruns@rotatingpenguin.com>
License-Expression: Apache-2.0
Project-URL: homepage, https://github.com/cmbruns/pyopenxr
Project-URL: bug_tracker, https://github.com/cmbruns/pyopenxr/issues
Keywords: OpenXR,VR,AR,bindings,Python,3D,graphics
Classifier: Development Status :: 4 - Beta
Classifier: Environment :: Win32 (MS Windows)
Classifier: Intended Audience :: Developers
Classifier: Intended Audience :: Science/Research
Classifier: Operating System :: Microsoft :: Windows
Classifier: Operating System :: POSIX :: Linux
Classifier: Programming Language :: Python :: 3 :: Only
Classifier: Programming Language :: Python :: Implementation :: CPython
Classifier: Topic :: Multimedia :: Graphics :: 3D Rendering
Classifier: Topic :: Scientific/Engineering :: Visualization
Requires-Python: >=3.9
License-File: LICENSE
Requires-Dist: glfw
Requires-Dist: numpy
Requires-Dist: PyOpenGL
Provides-Extra: generate
Requires-Dist: clang; extra == "generate"
Provides-Extra: test
Requires-Dist: pytest; extra == "test"
Provides-Extra: dev
Requires-Dist: libclang==12; extra == "dev"
Requires-Dist: PyOpenGL; extra == "dev"
Requires-Dist: glfw; extra == "dev"
Requires-Dist: numpy; extra == "dev"
Requires-Dist: pytest; extra == "dev"
Requires-Dist: nose2; extra == "dev"
Requires-Dist: sphinx; extra == "dev"
Requires-Dist: sphinx_rtd_theme; extra == "dev"
Requires-Dist: twine; extra == "dev"
Provides-Extra: glfw
Requires-Dist: glfw; extra == "glfw"
Provides-Extra: pyside
Requires-Dist: PySide6; extra == "pyside"
Dynamic: license-file
